cimcb/__init__.py
cimcb/__version__.py
cimcb/bootstrap/BC.py
cimcb/bootstrap/BCA.py
cimcb/bootstrap/BaseBootstrap.py
cimcb/bootstrap/Perc.py
cimcb/bootstrap/__init__.py
cimcb/cross_val/BaseCrossVal.py
cimcb/cross_val/BaseCrossVal_older.py
cimcb/cross_val/__init__.py
cimcb/cross_val/holdout.py
cimcb/cross_val/kfold.py
cimcb/cross_val/kfold_older.py
cimcb/model/BaseModel.py
cimcb/model/MBNN_LinearSigmoid.py
cimcb/model/MBNN_LinearSigmoid_1Layer.py
cimcb/model/MBNN_SigmoidSigmoid.py
cimcb/model/MBNN_SigmoidSigmoid_1Layer.py
cimcb/model/NN_L1.py
cimcb/model/NN_L2.py
cimcb/model/NN_LinearLinear.py
cimcb/model/NN_LinearLinear_Sklearn.py
cimcb/model/NN_LinearLogit.py
cimcb/model/NN_LinearLogit_Sklearn.py
cimcb/model/NN_LinearRelu.py
cimcb/model/NN_LinearSigmoid.py
cimcb/model/NN_LinearTan.py
cimcb/model/NN_LogitLinear.py
cimcb/model/NN_LogitLogit.py
cimcb/model/NN_LogitLogit_Sklearn.py
cimcb/model/NN_LogitRelu.py
cimcb/model/NN_LogitTan.py
cimcb/model/NN_ReluLinear.py
cimcb/model/NN_ReluLogit.py
cimcb/model/NN_ReluRelu.py
cimcb/model/NN_ReluTan.py
cimcb/model/NN_SigmoidSigmoid.py
cimcb/model/NN_SigmoidSigmoidSigmoid.py
cimcb/model/NN_SoftmaxSoftmax.py
cimcb/model/NN_TanLinear.py
cimcb/model/NN_TanLogit.py
cimcb/model/NN_TanRelu.py
cimcb/model/NN_TanTan.py
cimcb/model/PCLR.py
cimcb/model/PCR.py
cimcb/model/PLS_NIPALS.py
cimcb/model/PLS_SIMPLS.py
cimcb/model/RBF_NN.py
cimcb/model/RF.py
cimcb/model/SVM.py
cimcb/model/__init__.py
cimcb/plot/__init__.py
cimcb/plot/boxplot.py
cimcb/plot/distribution.py
cimcb/plot/pca.py
cimcb/plot/permutation_test.py
cimcb/plot/roc.py
cimcb/plot/scatter.py
cimcb/plot/scatterCI.py
cimcb/utils/YpredCallback.py
cimcb/utils/__init__.py
cimcb/utils/binary_metrics.py
cimcb/utils/ci95_ellipse.py
cimcb/utils/color_scale.py
cimcb/utils/dict_95ci.py
cimcb/utils/dict_mean.py
cimcb/utils/dict_median.py
cimcb/utils/dict_median_scores.py
cimcb/utils/dict_perc.py
cimcb/utils/dict_std.py
cimcb/utils/knnimpute.py
cimcb/utils/load_comparisonXL.py
cimcb-1.1.0.dist-info/LICENSE.txt
cimcb-1.1.0.dist-info/METADATA
cimcb-1.1.0.dist-info/WHEEL
cimcb-1.1.0.dist-info/top_level.txt
cimcb-1.1.0.dist-info/RECORD
