Metadata-Version: 2.1
Name: cimcb
Version: 1.1.0
Summary: This is a pre-release.
Home-page: https://github.com/KevinMMendez/cimcb
Author: Kevin Mendez, David Broadhurst
Author-email: k.mendez@ecu.edu.au, d.broadhurst@ecu.edu.au
License: http://www.apache.org/licenses/LICENSE-2.0.html
Platform: UNKNOWN
Requires-Python: >=3.5
Requires-Dist: bokeh (>=1.0.0)
Requires-Dist: keras
Requires-Dist: numpy (>=1.12)
Requires-Dist: pandas
Requires-Dist: scipy
Requires-Dist: scikit-learn
Requires-Dist: statsmodels
Requires-Dist: tensorflow
Requires-Dist: tqdm
Requires-Dist: xlrd
Requires-Dist: joblib
